et_al/__init__.py
foo_et_al/__init__.py
foo_et_al/foo_et_al.py
foo_et_al/utils.py
tests/__init__.py
tests/_test_example_contribution.py
tests/run_tests.py
tests/test_foo_et_al.py
foo_et_al_2-0.3.dist-info/LICENSE
foo_et_al_2-0.3.dist-info/METADATA
foo_et_al_2-0.3.dist-info/WHEEL
foo_et_al_2-0.3.dist-info/top_level.txt
foo_et_al_2-0.3.dist-info/RECORD
