Metadata-Version: 2.1
Name: foo_et_al_2
Version: 0.3
Summary: A python package for the Foo et al. parameterization, et al.
Author: Joseph Willem Ricci
Author-email: josephwillemricci@gmail.com
Classifier: Programming Language :: Python :: 3
Classifier: License :: OSI Approved :: MIT License
Classifier: Operating System :: OS Independent
Requires-Python: >=3.6
License-File: LICENSE
